[
	{
		"name": "Great Republic",
		"leaderName": "Ryan V",
		"adjective": ["People"],
		"startBias": ["River", "Coast", "Avoid [Tundra]"],
		"preferredVictoryType": "Cultural",
		
		"startIntroPart1": "",
		"startIntroPart2": "",
		
		"declaringWar": "sorry but i need more land for myself",
		"attacked": "how dare you... oh well",
		"defeated": "how embarrassing...",
		"introduction": "Hello Friend. It appear that there people existing here",
		
		"neutralHello": "Hi",
		"neutralLetsHearIt": ["Yeah?", "Alright lets see", "What i can help?"],
		"neutralNo": ["There no value in here", "Im not accepting it", "Can you give me more for this?"],
		"neutralYes": ["Alright i will accept it", "Very good trade yes?", "Hope this wil help!!"],

		"hateHello": "Hm? you here",
		"hateLetsHearIt": ["Alright what do you want", "Ok?", "You calling me for this?"],
		"hateNo": ["No.", "No way i would accept that!!", "Pardon me?"],
		"hateYes": ["Your luck was on your side.", "That is good enough.", "Very well..."],
		
		"afterPeace": "Very well I will stop my aggression",
		"tradeRequest": "Do this deal good for you?",

		"outerColor": [0, 21, 255],
	        "innerColor": [181, 12, 0],
		
		"uniqueName": "Legend of The Past",
		"uniques": ["May choose [1] additional belief(s) of any type when [founding] a religion","[+5 Gold] from every [Luxury resource]","[+2 Gold] from all [Culture] buildings","[-25]% tile improvement construction time","[-20]% Culture cost of adopting new Policies","[+2 Culture] from [Pasture] tiles [in all cities]","[+4 Production] from [Pasture] tiles [in all cities]","[+3 Food] from [Pasture] tiles [in all cities]","[+100]% Yield from every [Pasture]","Starts with [Animal Husbandry]","Receive free [Great Merchant] when you discover [Currency]"],
		 
	        "cities": ["Great City", "Wersa", "Frano", "Mirpo", "Qures", "Kali", "Cater", "Lomangan", "Iodan", "Prutor", "Youna", "Zaroone"]
	},
]

